shareboard/__init__.py
shareboard/__main__.py
shareboard/app.py
shareboard/models.py
shareboard/network.py
shareboard/storage.py
shareboard/ui/__init__.py
shareboard/ui/board.py
shareboard/ui/sidebar.py
shareboard/ui/styles.py
shareboard/ui/widgets.py
decentmesh_shareboard-0.3.6.dist-info/METADATA
decentmesh_shareboard-0.3.6.dist-info/WHEEL
decentmesh_shareboard-0.3.6.dist-info/entry_points.txt
decentmesh_shareboard-0.3.6.dist-info/RECORD
