Metadata-Version: 2.4
Name: decentmesh-shareboard
Version: 0.3.6
Summary: Decentralized copy-paste sharing application for DecentMesh
License: MIT
Classifier: Development Status :: 3 - Alpha
Classifier: Environment :: X11 Applications :: Qt
Classifier: Intended Audience :: End Users/Desktop
Classifier: License :: OSI Approved :: MIT License
Classifier: Programming Language :: Python :: 3
Classifier: Programming Language :: Python :: 3.9
Classifier: Programming Language :: Python :: 3.10
Classifier: Programming Language :: Python :: 3.11
Classifier: Programming Language :: Python :: 3.12
Classifier: Topic :: Communications
Requires-Python: >=3.9
Requires-Dist: cbor2>=5.6.0
Requires-Dist: cryptography>=41.0.0
Requires-Dist: decent-python-bridge>=0.1.6
Requires-Dist: pyside6>=6.5.0
Provides-Extra: dev
Requires-Dist: pytest>=7.0.0; extra == 'dev'
